histoprep/__init__.py
histoprep/_backend.py
histoprep/_cli.py
histoprep/_data.py
histoprep/_reader.py
histoprep/functional/__init__.py
histoprep/functional/_check.py
histoprep/functional/_concurrent.py
histoprep/functional/_dearray.py
histoprep/functional/_draw.py
histoprep/functional/_images.py
histoprep/functional/_level.py
histoprep/functional/_mean_std.py
histoprep/functional/_metrics.py
histoprep/functional/_normalize.py
histoprep/functional/_tiles.py
histoprep/functional/_tissue.py
histoprep/utils/__init__.py
histoprep/utils/_normalize.py
histoprep/utils/_process.py
histoprep/utils/_torch.py
histoprep-2.0.5.dist-info/LICENSE
histoprep-2.0.5.dist-info/METADATA
histoprep-2.0.5.dist-info/WHEEL
histoprep-2.0.5.dist-info/entry_points.txt
histoprep-2.0.5.dist-info/RECORD
