Metadata-Version: 2.1
Name: histoprep
Version: 2.0.5
Summary: Read and process histological slide images with python!
Author: jopo666
Author-email: jopo@birdlover.com
Requires-Python: >=3.9,<4.0
Classifier: Programming Language :: Python :: 3
Classifier: Programming Language :: Python :: 3.9
Classifier: Programming Language :: Python :: 3.10
Classifier: Programming Language :: Python :: 3.11
Requires-Dist: aicspylibczi (>=3,<4)
Requires-Dist: matplotlib
Requires-Dist: mpire (>=2.6,<3.0)
Requires-Dist: numpy
Requires-Dist: opencv-python-headless (>=4,<5)
Requires-Dist: openslide-python (>=1.2,<2.0)
Requires-Dist: pillow (>=9,<10)
Requires-Dist: polars (>=0.16,<0.17)
Requires-Dist: rich-click (>=1.6,<2.0)
Requires-Dist: scikit-learn (>=1,<2)
Requires-Dist: tqdm
